{
  "$schema": "https://www.style-dictionary.dev/schema/token.json",
  "_meta": {
    "generated": "2026-04-28",
    "source": "_state.tsx → COLORS / RADIUS / TRANSITION / SPACE / Z / FONTS",
    "tool": "Style Dictionary (https://styledictionary.com)"
  },
  "color": {
    "surface": {
      "$value": "#FAFAF7",
      "$type": "color",
      "$description": "Page / shell background"
    },
    "surfaceAlt": {
      "$value": "#F2F2EE",
      "$type": "color",
      "$description": "Secondary surfaces: table headers, hero/starter cards"
    },
    "card": {
      "$value": "#FFFFFF",
      "$type": "color",
      "$description": "Card background"
    },
    "ink": {
      "$value": "#0B0B0D",
      "$type": "color",
      "$description": "Primary text"
    },
    "inkMuted": {
      "$value": "rgba(11,11,13,0.72)",
      "$type": "color",
      "$description": "Secondary text, captions"
    },
    "inkDim": {
      "$value": "rgba(11,11,13,0.38)",
      "$type": "color",
      "$description": "Timestamps, disabled, placeholders"
    },
    "border": {
      "$value": "rgba(24,24,27,0.10)",
      "$type": "color",
      "$description": "Standard card border"
    },
    "borderSoft": {
      "$value": "rgba(24,24,27,0.06)",
      "$type": "color",
      "$description": "Dividers, subtle separators"
    },
    "borderStrong": {
      "$value": "rgba(24,24,27,0.20)",
      "$type": "color",
      "$description": "Hover/active card border"
    },
    "accent": {
      "$value": "#0F4F3E",
      "$type": "color",
      "$description": "Primary CTA, forest green — also aliased as brand"
    },
    "accentDeep": {
      "$value": "#093328",
      "$type": "color",
      "$description": "Accent on soft fills"
    },
    "accentSoft": {
      "$value": "rgba(15,79,62,0.10)",
      "$type": "color",
      "$description": "Accent background fill"
    },
    "brand": {
      "$value": "#0F4F3E",
      "$type": "color",
      "$description": "Semantic alias for accent — wayfinding, focus rings"
    },
    "brandSoft": {
      "$value": "rgba(15,79,62,0.10)",
      "$type": "color",
      "$description": "Brand background fill"
    },
    "brandDeep": {
      "$value": "#093328",
      "$type": "color",
      "$description": "Brand text on soft fill"
    },
    "success": {
      "$value": "#2E7D5B",
      "$type": "color",
      "$description": "Completed, paid, confirmed, approved"
    },
    "successSoft": {
      "$value": "rgba(46,125,91,0.10)",
      "$type": "color",
      "$description": "Success background fill"
    },
    "successDeep": {
      "$value": "#1F5D43",
      "$type": "color",
      "$description": "Success text on soft fill"
    },
    "amber": {
      "$value": "#52606D",
      "$type": "color",
      "$description": "Caution/draft — muted slate (NOT warm gold)"
    },
    "amberSoft": {
      "$value": "rgba(82,96,109,0.10)",
      "$type": "color",
      "$description": "Caution background fill"
    },
    "amberDeep": {
      "$value": "#3A4651",
      "$type": "color",
      "$description": "Caution text on soft fill"
    },
    "coral": {
      "$value": "#C26A45",
      "$type": "color",
      "$description": "Soft urgency — awaiting reply, expiring"
    },
    "coralSoft": {
      "$value": "rgba(194,106,69,0.10)",
      "$type": "color",
      "$description": "Coral background fill"
    },
    "coralDeep": {
      "$value": "#7A4128",
      "$type": "color",
      "$description": "Coral text on soft fill"
    },
    "critical": {
      "$value": "#B0303A",
      "$type": "color",
      "$description": "Destructive, broken, irreversible — max 1/week typical user"
    },
    "criticalSoft": {
      "$value": "rgba(176,48,58,0.10)",
      "$type": "color",
      "$description": "Critical background fill"
    },
    "criticalDeep": {
      "$value": "#7E1F26",
      "$type": "color",
      "$description": "Critical text on soft fill"
    },
    "indigo": {
      "$value": "#5B6BA0",
      "$type": "color",
      "$description": "Analytics, in-flight status, system messaging"
    },
    "indigoSoft": {
      "$value": "rgba(91,107,160,0.10)",
      "$type": "color",
      "$description": "Info background fill"
    },
    "indigoDeep": {
      "$value": "#3F4870",
      "$type": "color",
      "$description": "Info text on soft fill"
    },
    "royal": {
      "$value": "#5F4B8B",
      "$type": "color",
      "$description": "Premium tier, paid feature, AI assist — max 2/screen"
    },
    "royalSoft": {
      "$value": "rgba(95,75,139,0.10)",
      "$type": "color",
      "$description": "Premium background fill"
    },
    "royalDeep": {
      "$value": "#3D2F61",
      "$type": "color",
      "$description": "Premium text on soft fill"
    },
    "shadow": {
      "$value": "0 1px 2px rgba(11,11,13,0.04)",
      "$type": "shadow",
      "$description": "Default card elevation"
    },
    "shadowHover": {
      "$value": "0 6px 18px rgba(11,11,13,0.08)",
      "$type": "shadow",
      "$description": "Card hover elevation"
    },
    "navyBg": {
      "$value": "#0B0B0D",
      "$type": "color",
      "$description": "Dark nav background"
    }
  },
  "radius": {
    "sm": {
      "$value": "7px",
      "$type": "dimension",
      "$description": "Chips, inline pills, small inputs"
    },
    "md": {
      "$value": "10px",
      "$type": "dimension",
      "$description": "Buttons, dense cards"
    },
    "lg": {
      "$value": "12px",
      "$type": "dimension",
      "$description": "Cards, modals, drawers"
    },
    "xl": {
      "$value": "16px",
      "$type": "dimension",
      "$description": "Hero / spotlight cards"
    }
  },
  "transition": {
    "micro": {
      "$value": "120ms linear",
      "$type": "transition",
      "$description": "Instant hover colour/bg swap — 120ms, no easing"
    },
    "sm": {
      "$value": "150ms ease",
      "$type": "transition",
      "$description": "Small opacity/border state change"
    },
    "md": {
      "$value": "180ms ease",
      "$type": "transition",
      "$description": "Badge/pill expand, component enter/exit"
    },
    "layout": {
      "$value": "220ms ease-out",
      "$type": "transition",
      "$description": "Sidebar expand, grid column resize"
    },
    "drawer": {
      "$value": "260ms cubic-bezier(0.4, 0, 0.2, 1)",
      "$type": "transition",
      "$description": "Sheet/panel slides — material decelerate"
    }
  },
  "spacing": {
    "tight": {
      "$value": "8px",
      "$type": "dimension",
      "$description": "Between dense sibling cards"
    },
    "block": {
      "$value": "12px",
      "$type": "dimension",
      "$description": "Default sibling gap"
    },
    "group": {
      "$value": "24px",
      "$type": "dimension",
      "$description": "Between metric strip and rich panels"
    },
    "section": {
      "$value": "32px",
      "$type": "dimension",
      "$description": "Between top-level page sections"
    }
  },
  "zIndex": {
    "topbar": {
      "$value": 40,
      "$type": "other",
      "$description": "Top navigation bar"
    },
    "controlBar": {
      "$value": 100,
      "$type": "other",
      "$description": "Sticky control bars inside pages"
    },
    "drawerBackdrop": {
      "$value": 200,
      "$type": "other",
      "$description": "Drawer backdrop overlay"
    },
    "drawerPanel": {
      "$value": 210,
      "$type": "other",
      "$description": "Drawer panel"
    },
    "modalBackdrop": {
      "$value": 300,
      "$type": "other",
      "$description": "Modal backdrop"
    },
    "modalPanel": {
      "$value": 310,
      "$type": "other",
      "$description": "Modal panel"
    },
    "toast": {
      "$value": 400,
      "$type": "other",
      "$description": "Toast notifications"
    }
  },
  "font": {
    "display": {
      "$value": "var(--font-geist-sans), \"Inter\", -apple-system, BlinkMacSystemFont, \"SF Pro Display\", system-ui, sans-serif",
      "$type": "fontFamily",
      "$description": "Page H1, drawer titles, hero numbers"
    },
    "body": {
      "$value": "\"Inter\", system-ui, sans-serif",
      "$type": "fontFamily",
      "$description": "All body copy, labels, chips"
    },
    "mono": {
      "$value": "ui-monospace, \"SF Mono\", Menlo, monospace",
      "$type": "fontFamily",
      "$description": "Code blocks, IDs, ref numbers"
    }
  }
}
